TODO_LIST_CLI_ldriver/Task.py
TODO_LIST_CLI_ldriver/ToDoList.py
TODO_LIST_CLI_ldriver/__init__.py
TODO_LIST_CLI_ldriver/file.txt
TODO_LIST_CLI_ldriver/main.py
todo_list_cli_ldriver-0.0.5.dist-info/METADATA
todo_list_cli_ldriver-0.0.5.dist-info/WHEEL
todo_list_cli_ldriver-0.0.5.dist-info/licenses/LICENSE
todo_list_cli_ldriver-0.0.5.dist-info/RECORD
